LICENSE
README.md
setup.py
yaookctl/__init__.py
yaookctl/__main__.py
yaookctl/cli.py
yaookctl/cliutil.py
yaookctl/completion.py
yaookctl/data.py
yaookctl/debugger.py
yaookctl/galera.py
yaookctl/logs.py
yaookctl/lookups.py
yaookctl/ovsdb.py
yaookctl/status.py
yaookctl.egg-info/PKG-INFO
yaookctl.egg-info/SOURCES.txt
yaookctl.egg-info/dependency_links.txt
yaookctl.egg-info/entry_points.txt
yaookctl.egg-info/requires.txt
yaookctl.egg-info/top_level.txt